ansible_docsmith/__init__.py
ansible_docsmith/cli.py
ansible_docsmith/constants.py
ansible_docsmith/core/__init__.py
ansible_docsmith/core/exceptions.py
ansible_docsmith/core/generator.py
ansible_docsmith/core/parser.py
ansible_docsmith/core/processor.py
ansible_docsmith/templates/__init__.py
ansible_docsmith/templates/readme/__init__.py
ansible_docsmith/templates/readme/default.md.j2
ansible_docsmith/templates/readme/default.rst.j2
ansible_docsmith/utils/__init__.py
ansible_docsmith/utils/logging.py
ansible_docsmith-2.0.0.dist-info/licenses/LICENSES/GPL-3.0-or-later.txt
ansible_docsmith-2.0.0.dist-info/WHEEL
ansible_docsmith-2.0.0.dist-info/entry_points.txt
ansible_docsmith-2.0.0.dist-info/METADATA
ansible_docsmith-2.0.0.dist-info/RECORD
