Metadata-Version: 2.4
Name: ansible-docsmith
Version: 2.0.0
Summary: DocSmith for Ansible: automating role documentation (using argument_specs.yml)
Keywords: ansible,documentation,yaml,cli,automation
Author: foundata GmbH, Andreas Haerter
Author-email: Andreas Haerter <ah@foundata.com>
License-Expression: GPL-3.0-or-later
License-File: LICENSES/GPL-3.0-or-later.txt
Classifier: Development Status :: 5 - Production/Stable
Classifier: License :: OSI Approved :: GNU General Public License v3 or later (GPLv3+)
Classifier: Environment :: Console
Classifier: Intended Audience :: Developers
Classifier: Intended Audience :: System Administrators
Classifier: Topic :: Documentation
Classifier: Topic :: Software Development :: Documentation
Classifier: Topic :: System :: Systems Administration
Classifier: Topic :: Utilities
Classifier: Programming Language :: Python :: 3
Classifier: Programming Language :: Python :: 3.11
Classifier: Programming Language :: Python :: 3.12
Classifier: Programming Language :: Python :: 3.13
Requires-Dist: commonmark>=0.9.1
Requires-Dist: jinja2>=3.1.6
Requires-Dist: pydantic>=2.11.7
Requires-Dist: rich>=14.1.0
Requires-Dist: ruamel-yaml>=0.18.14
Requires-Dist: typer>=0.16.0
Maintainer: Andreas Haerter
Maintainer-email: Andreas Haerter <ah@foundata.com>
Requires-Python: >=3.11
Project-URL: Changelog, https://foundata.com/en/projects/ansible-docsmith/#changelog
Project-URL: Documentation, https://foundata.com/en/projects/ansible-docsmith/#doc
Project-URL: Homepage, https://foundata.com/en/projects/ansible-docsmith/
Project-URL: Issues, https://foundata.com/en/projects/ansible-docsmith/#issues
Project-URL: Repository, https://foundata.com/en/projects/ansible-docsmith/#source
